README.md
pyproject.toml
setup.cfg
setup.py
bin/sdbmigrate.py
sdbmigrate-1.1.3.data/scripts/sdbmigrate.py
sdbmigrate.egg-info/PKG-INFO
sdbmigrate.egg-info/SOURCES.txt
sdbmigrate.egg-info/dependency_links.txt
sdbmigrate.egg-info/requires.txt
sdbmigrate.egg-info/top_level.txt
sdbmigrate-1.1.3.dist-info/METADATA
sdbmigrate-1.1.3.dist-info/WHEEL
sdbmigrate-1.1.3.dist-info/top_level.txt
sdbmigrate-1.1.3.dist-info/RECORD
